Globals/GlobalFunctions.py
Globals/__init__.py
SpamEmailDetector-0.1.0.dist-info/LICENSE.txt
SpamEmailDetector-0.1.0.dist-info/METADATA
SpamEmailDetector-0.1.0.dist-info/WHEEL
SpamEmailDetector-0.1.0.dist-info/top_level.txt
SpamEmailDetector-0.1.0.dist-info/RECORD
