Metadata-Version: 2.1
Name: SpamEmailDetector
Version: 0.1.0
Summary: This is a package for detecting spam emails and normal emails. Codes included will continuesly listen to the provided email address, and will return message when a new email is received
Home-page: https://github.com/NathanHuXy/SpamEmailDetector
Author: Xueyan Hu
Author-email: xueyanhu1231@163.com
Classifier: Programming Language :: Python :: 3
Classifier: License :: OSI Approved :: MIT License
Classifier: Operating System :: OS Independent
Requires-Python: >=3.10
License-File: LICENSE.txt
